dg_clt/__init__.py
dg_clt/menus.py
dg_clt/screen.py
dg_clt-0.2.0.dist-info/METADATA
dg_clt-0.2.0.dist-info/WHEEL
dg_clt-0.2.0.dist-info/top_level.txt
dg_clt-0.2.0.dist-info/RECORD
