Metadata-Version: 2.4
Name: dg-clt
Version: 0.2.0
Summary: The Dazed Gerbil's Command Line Tools
Author-email: Calum Andrew Morrell <calum@drulum.com>
License-Expression: GPL-3.0-or-later
Classifier: Development Status :: 1 - Planning
Classifier: Environment :: Console
Classifier: Intended Audience :: Developers
Classifier: Operating System :: OS Independent
Classifier: Topic :: Software Development :: Libraries
Classifier: Topic :: Software Development :: Libraries :: Python Modules
Classifier: Topic :: Software Development :: User Interfaces
Requires-Python: >=3.10
